clongro/__init__.py
clongro/__main__.py
clongro/cli.py
clongro/core.py
clongro/utils.py
clongro-0.1.4.dist-info/licenses/LICENSE
clongro-0.1.4.dist-info/METADATA
clongro-0.1.4.dist-info/WHEEL
clongro-0.1.4.dist-info/entry_points.txt
clongro-0.1.4.dist-info/top_level.txt
clongro-0.1.4.dist-info/RECORD
