Metadata-Version: 2.4
Name: clongro
Version: 0.1.4
Summary: Simple tool to estimate the exponential growth rate of each clone in a barcoded cell population.
Author-email: "Andrea (Didi) Gardner" <andrealgardner@utexas.edu>
Maintainer-email: "Andrea (Didi) Gardner" <andrealgardner@utexas.edu>
License: MIT license
Project-URL: bugs, https://github.com/andrealgardner/clongro/issues
Project-URL: changelog, https://github.com/andrealgardner/clongro/blob/master/changelog.md
Project-URL: homepage, https://github.com/andrealgardner/clongro
License-File: LICENSE
Requires-Dist: polars>=1.26.0
Requires-Dist: typer>=0.15.2
Provides-Extra: dev
Requires-Dist: ruff; extra == "dev"
Dynamic: license-file
